[1,["12931cef1@6c48a"],["_textureSource"],["cc.SpriteFrame","cc.SpriteAtlas"],0,[[[{"name":"CONGRATS","rect":{"x":3,"y":506,"width":312,"height":95},"offset":{"x":0,"y":1},"originalSize":{"width":422,"height":101},"rotated":false,"capInsets":[0,0,0,0],"packable":true,"pixelsToUnit":100,"pivot":{"x":0.5,"y":0.5},"meshType":0}],[0],0,[0],[0],[0]],[[{"name":"BG_Compliment_CONGRATS","rect":{"x":403,"y":506,"width":227,"height":75},"offset":{"x":-2,"y":0},"originalSize":{"width":481,"height":81},"rotated":true,"capInsets":[0,0,0,0],"packable":true,"pixelsToUnit":100,"pivot":{"x":0.5,"y":0.5},"meshType":0}],[0],0,[0],[0],[0]],[[{"name":"FG_Compliment_CONGRATS","rect":{"x":321,"y":506,"width":226,"height":76},"offset":{"x":-1.5,"y":0.5},"originalSize":{"width":481,"height":81},"rotated":true,"capInsets":[0,0,0,0],"packable":true,"pixelsToUnit":100,"pivot":{"x":0.5,"y":0.5},"meshType":0}],[0],0,[0],[0],[0]],[[{"name":"WAYS","rect":{"x":563,"y":369,"width":48,"height":27},"offset":{"x":-0.5,"y":0},"originalSize":{"width":135,"height":27},"rotated":true,"capInsets":[0,0,0,0],"packable":true,"pixelsToUnit":100,"pivot":{"x":0.5,"y":0.5},"meshType":0}],[0],0,[0],[0],[0]],[[{"name":"FG_Compliment_FREESPINS","rect":{"x":249,"y":607,"width":94,"height":36},"offset":{"x":-0.5,"y":-0.5},"originalSize":{"width":241,"height":41},"rotated":true,"capInsets":[0,0,0,0],"packable":true,"pixelsToUnit":100,"pivot":{"x":0.5,"y":0.5},"meshType":0}],[0],0,[0],[0],[0]],[[{"name":"FG_FREEGAME","rect":{"x":699,"y":652,"width":85,"height":33},"offset":{"x":-1,"y":-2},"originalSize":{"width":135,"height":51},"rotated":true,"capInsets":[0,0,0,0],"packable":true,"pixelsToUnit":100,"pivot":{"x":0.5,"y":0.5},"meshType":0}],[0],0,[0],[0],[0]],[[{"name":"AutoPlay","rect":{"x":3,"y":607,"width":240,"height":42},"offset":{"x":-1,"y":0},"originalSize":{"width":360,"height":56},"rotated":false,"capInsets":[0,0,0,0],"packable":true,"pixelsToUnit":100,"pivot":{"x":0.5,"y":0.5},"meshType":0}],[0],0,[0],[0],[0]],[[{"name":"BERSERK_MODE_1","rect":{"x":613,"y":369,"width":369,"height":80},"offset":{"x":1,"y":0},"originalSize":{"width":511,"height":80},"rotated":true,"capInsets":[0,0,0,0],"packable":true,"pixelsToUnit":100,"pivot":{"x":0.5,"y":0.5},"meshType":0}],[0],0,[0],[0],[0]],[[{"name":"GameTextImg","spriteFrames":["String_01","f40SC7E8xF0JwfvqNHcc0p@f9941","txt2","e62C4+2m1AEYysEORMu+3F@f9941","FREESPINS","e2+/85RT9NJpeCIaQR79FC@f9941","BG_Declar_Free","8b4UDFoiNLqLasjY8quQLJ@f9941","BERSERK_MODE_1","58KNq2e31BUrMM2lGVLRHN@f9941","txt1","d8BJy7sm5DSrD/vS50seNs@f9941","WAYS","27WpUVIXxGIofFc1XGqFhM@f9941","BERSERK_MODE_2","8fGdCG3HNPVLFEmAb1wCk6@f9941","FG_FREEGAME","470E+1bkVIzIQm2AG0UGrm@f9941","CONGRATS","03lL4vypZN5ZrAjhe23o9v@f9941","FG_Compliment_CONGRATS","14xw3MHItKX4UXhPfXV0UY@f9941","BG_Compliment_CONGRATS","121/3PdA5AlIVZbiRhnCMq@f9941","BG_Compliment_INBONUS_GAME","dfLY3aiF9GAqM5QZIXwMhZ@f9941","FREEGAME","a26niHPeZKApyPraxxMsHZ@f9941","AutoPlay","56fKtLSVZDfZIko8PzbDFU@f9941","FG_Compliment_FREESPINS","28KoVADnxM8rIpmVlSKtgP@f9941","String_00","f89j1uuLpDsKPtj6G6NrHG@f9941","Auto","ac8ka6JVNNyLRv6vqdslI7@f9941","BG_Compliment_YOUVE_WON","dbc1aUi1FPLpzu3VH6EcoO@f9941"]}],[1],0,[],[],[]],[[{"name":"BG_Declar_Free","rect":{"x":563,"y":3,"width":360,"height":93},"offset":{"x":4.5,"y":-3.5},"originalSize":{"width":531,"height":100},"rotated":true,"capInsets":[0,0,0,0],"packable":true,"pixelsToUnit":100,"pivot":{"x":0.5,"y":0.5},"meshType":0}],[0],0,[0],[0],[0]],[[{"name":"BERSERK_MODE_2","rect":{"x":699,"y":365,"width":281,"height":42},"offset":{"x":-1,"y":0.5},"originalSize":{"width":549,"height":45},"rotated":true,"capInsets":[0,0,0,0],"packable":true,"pixelsToUnit":100,"pivot":{"x":0.5,"y":0.5},"meshType":0}],[0],0,[0],[0],[0]],[[{"name":"FREEGAME","rect":{"x":484,"y":506,"width":114,"height":35},"offset":{"x":-0.5,"y":1},"originalSize":{"width":135,"height":67},"rotated":true,"capInsets":[0,0,0,0],"packable":true,"pixelsToUnit":100,"pivot":{"x":0.5,"y":0.5},"meshType":0}],[0],0,[0],[0],[0]],[[{"name":"Auto","rect":{"x":208,"y":655,"width":85,"height":29},"offset":{"x":1,"y":0},"originalSize":{"width":135,"height":35},"rotated":true,"capInsets":[0,0,0,0],"packable":true,"pixelsToUnit":100,"pivot":{"x":0.5,"y":0.5},"meshType":0}],[0],0,[0],[0],[0]],[[{"name":"txt1","rect":{"x":662,"y":3,"width":356,"height":56},"offset":{"x":0,"y":0},"originalSize":{"width":470,"height":56},"rotated":true,"capInsets":[0,0,0,0],"packable":true,"pixelsToUnit":100,"pivot":{"x":0.5,"y":0.5},"meshType":0}],[0],0,[0],[0],[0]],[[{"name":"BG_Compliment_YOUVE_WON","rect":{"x":3,"y":706,"width":93,"height":28},"offset":{"x":0,"y":-0.5},"originalSize":{"width":241,"height":41},"rotated":false,"capInsets":[0,0,0,0],"packable":true,"pixelsToUnit":100,"pivot":{"x":0.5,"y":0.5},"meshType":0}],[0],0,[0],[0],[0]],[[{"name":"BG_Compliment_INBONUS_GAME","rect":{"x":484,"y":711,"width":117,"height":28},"offset":{"x":-1,"y":-3.5},"originalSize":{"width":241,"height":41},"rotated":false,"capInsets":[0,0,0,0],"packable":true,"pixelsToUnit":100,"pivot":{"x":0.5,"y":0.5},"meshType":0}],[0],0,[0],[0],[0]],[[{"name":"FREESPINS","rect":{"x":525,"y":458,"width":247,"height":82},"offset":{"x":-7.5,"y":-3.5},"originalSize":{"width":422,"height":101},"rotated":true,"capInsets":[0,0,0,0],"packable":true,"pixelsToUnit":100,"pivot":{"x":0.5,"y":0.5},"meshType":0}],[0],0,[0],[0],[0]],[[{"name":"txt2","rect":{"x":525,"y":3,"width":449,"height":32},"offset":{"x":-0.5,"y":0},"originalSize":{"width":470,"height":56},"rotated":true,"capInsets":[0,0,0,0],"packable":true,"pixelsToUnit":100,"pivot":{"x":0.5,"y":0.5},"meshType":0}],[0],0,[0],[0],[0]],[[{"name":"String_01","rect":{"x":3,"y":3,"width":516,"height":497},"offset":{"x":-26.5,"y":3.5},"originalSize":{"width":579,"height":524},"rotated":false,"capInsets":[0,0,0,0],"packable":true,"pixelsToUnit":100,"pivot":{"x":0.5,"y":0.5},"meshType":0}],[0],0,[0],[0],[0]],[[{"name":"String_00","rect":{"x":3,"y":655,"width":199,"height":45},"offset":{"x":0,"y":-0.5},"originalSize":{"width":579,"height":54},"rotated":false,"capInsets":[0,0,0,0],"packable":true,"pixelsToUnit":100,"pivot":{"x":0.5,"y":0.5},"meshType":0}],[0],0,[0],[0],[0]]]]
